MANIFEST.in
README.md
readme_example_plot.png
requirements.txt
setup.py
src/sinter/__init__.py
src/sinter/_plotting.py
src/sinter/_plotting_test.py
src/sinter/_predict.py
src/sinter/_predict_test.py
src/sinter/_probability_util.py
src/sinter/_probability_util_test.py
src/sinter.egg-info/PKG-INFO
src/sinter.egg-info/SOURCES.txt
src/sinter.egg-info/dependency_links.txt
src/sinter.egg-info/entry_points.txt
src/sinter.egg-info/requires.txt
src/sinter.egg-info/top_level.txt
src/sinter/_collection/__init__.py
src/sinter/_collection/_collection.py
src/sinter/_collection/_collection_manager.py
src/sinter/_collection/_collection_manager_test.py
src/sinter/_collection/_collection_test.py
src/sinter/_collection/_collection_worker_loop.py
src/sinter/_collection/_collection_worker_state.py
src/sinter/_collection/_collection_worker_test.py
src/sinter/_collection/_mux_sampler.py
src/sinter/_collection/_printer.py
src/sinter/_collection/_sampler_ramp_throttled.py
src/sinter/_collection/_sampler_ramp_throttled_test.py
src/sinter/_command/__init__.py
src/sinter/_command/_main.py
src/sinter/_command/_main_collect.py
src/sinter/_command/_main_collect_test.py
src/sinter/_command/_main_combine.py
src/sinter/_command/_main_combine_test.py
src/sinter/_command/_main_plot.py
src/sinter/_command/_main_plot_test.py
src/sinter/_command/_main_predict.py
src/sinter/_command/_main_predict_test.py
src/sinter/_data/__init__.py
src/sinter/_data/_anon_task_stats.py
src/sinter/_data/_anon_task_stats_test.py
src/sinter/_data/_collection_options.py
src/sinter/_data/_collection_options_test.py
src/sinter/_data/_csv_out.py
src/sinter/_data/_existing_data.py
src/sinter/_data/_existing_data_test.py
src/sinter/_data/_task.py
src/sinter/_data/_task_stats.py
src/sinter/_data/_task_stats_test.py
src/sinter/_data/_task_test.py
src/sinter/_decoding/__init__.py
src/sinter/_decoding/_decoding.py
src/sinter/_decoding/_decoding_all_built_in_decoders.py
src/sinter/_decoding/_decoding_decoder_class.py
src/sinter/_decoding/_decoding_fusion_blossom.py
src/sinter/_decoding/_decoding_mwpf.py
src/sinter/_decoding/_decoding_pymatching.py
src/sinter/_decoding/_decoding_test.py
src/sinter/_decoding/_decoding_vacuous.py
