Metadata-Version: 2.4
Name: sinter
Version: 1.16.dev1768882982
Summary: Samples stim circuits and decodes them using pymatching.
Author: Craig Gidney
Author-email: craig.gidney@gmail.com
License: Apache 2
Requires-Python: >=3.7.0
Requires-Dist: matplotlib
Requires-Dist: numpy
Requires-Dist: stim
Requires-Dist: scipy
Dynamic: author
Dynamic: author-email
Dynamic: description
Dynamic: description-content-type
Dynamic: license
Dynamic: requires-dist
Dynamic: requires-python
Dynamic: summary
